{
  "predata_hash": "1e14ec65301a9378bfc91cebc460385d",
  "predata_updated": "2025-09-20T01:30:10.433646",
  "chunk_configs": {
    "chunks_800_100": {
      "created": "2025-09-15T18:11:37.231378",
      "chunks_count": 260
    }
  },
  "guidelines_hash": "0011bf71e6c7d7fe38b3edf601cba71e",
  "guidelines_updated": "2025-09-15T18:12:36.721332",
  "guidelines_size": 260,
  "basic_templates_hash": "d89d8794690d37db1b521fafba8d6671",
  "basic_templates_updated": "2025-09-17T09:03:34.647178",
  "basic_templates_size": 168
}